trader/__init__.py
trader/version.py
trader-0.0.0.dist-info/METADATA
trader-0.0.0.dist-info/WHEEL
trader-0.0.0.dist-info/top_level.txt
trader-0.0.0.dist-info/RECORD
